clarc/__init__.py
clarc/__main__.py
clarc/clarc.py
clarc/cli.py
clarc-1.0.0.dist-info/LICENSE
clarc-1.0.0.dist-info/METADATA
clarc-1.0.0.dist-info/WHEEL
clarc-1.0.0.dist-info/dependency_links.txt
clarc-1.0.0.dist-info/entry_points.txt
clarc-1.0.0.dist-info/top_level.txt
clarc-1.0.0.dist-info/RECORD
