Metadata-Version: 2.1
Name: clarc
Version: 1.0.0
Summary: A simple command-line tool to archive data
Home-page: https://github.com/sandiemann/clarc-cli
Author: Sanchit Bhavsar
Author-email: sanchit.bhavsar@gmail.com
License: MIT
Download-URL: https://github.com/sandiemann/clarc-cli/archive/1.0.0.tar.gz
Platform: UNKNOWN
Classifier: License :: OSI Approved :: MIT License
Classifier: Programming Language :: Python :: 2.7
Classifier: Programming Language :: Python :: 3
Classifier: Programming Language :: Python :: 3.7
Requires-Python: >=2.7
License-File: LICENSE
Requires-Dist: typer (==0.4.0)
Requires-Dist: colorama (==0.4.4)
Requires-Dist: shellingham (==1.4.0)
Requires-Dist: pytest (==6.2.4)
